python_sdk_client/__init__.py
python_sdk_client/clients_enum.py
python_sdk_client/cropin_api.py
python_sdk_client/libs/__init__.py
python_sdk_client/libs/abstract_client.py
python_sdk_client/libs/batch_processor.py
python_sdk_client/libs/client_cfg.py
python_sdk_client/libs/cropin_client.py
python_sdk_client/libs/cropin_exceptions.py
python_sdk_client/libs/insight_service_client.py
python_sdk_client/libs/keycloak_client.py
tests/__init__.py
tests/cropin_api_test.py
cropin_plotrisk_insight_client-0.2.0.dist-info/METADATA
cropin_plotrisk_insight_client-0.2.0.dist-info/WHEEL
cropin_plotrisk_insight_client-0.2.0.dist-info/top_level.txt
cropin_plotrisk_insight_client-0.2.0.dist-info/RECORD
