Metadata-Version: 2.1
Name: cropin-plotrisk-insight-client
Version: 0.2.0
Summary: Insights Service API
Home-page: 
Author-email: 
Keywords: Insights Service API -test
Requires-Dist: urllib3 (>=1.15)
Requires-Dist: six (>=1.10)
Requires-Dist: certifi
Requires-Dist: python-dateutil
Requires-Dist: plotrisk-sfplus-internal-client (>=0.1.0)
